odoo/addons/pms_account_asset/README.rst
odoo/addons/pms_account_asset/__init__.py
odoo/addons/pms_account_asset/__manifest__.py
odoo/addons/pms_account_asset/i18n/es.po
odoo/addons/pms_account_asset/i18n/pms_account_asset.pot
odoo/addons/pms_account_asset/models/__init__.py
odoo/addons/pms_account_asset/models/account_asset.py
odoo/addons/pms_account_asset/models/pms_property.py
odoo/addons/pms_account_asset/readme/CONFIGURE.rst
odoo/addons/pms_account_asset/readme/CONTRIBUTORS.rst
odoo/addons/pms_account_asset/readme/DESCRIPTION.rst
odoo/addons/pms_account_asset/readme/USAGE.rst
odoo/addons/pms_account_asset/static/description/icon.png
odoo/addons/pms_account_asset/static/description/index.html
odoo/addons/pms_account_asset/views/account_asset.xml
odoo/addons/pms_account_asset/views/menu.xml
odoo/addons/pms_account_asset/views/pms_property.xml
odoo14_addon_pms_account_asset-14.0.1.0.1.dev2.dist-info/METADATA
odoo14_addon_pms_account_asset-14.0.1.0.1.dev2.dist-info/WHEEL
odoo14_addon_pms_account_asset-14.0.1.0.1.dev2.dist-info/top_level.txt
odoo14_addon_pms_account_asset-14.0.1.0.1.dev2.dist-info/RECORD
